setup.py
dops_util/__init__.py
dops_util/ami.py
dops_util/cloudtrail.py
dops_util/connect.py
dops_util/cost_saving.py
dops_util/cw.py
dops_util/dms.py
dops_util/dynamo.py
dops_util/ebs.py
dops_util/ebs_snapshot.py
dops_util/ec2.py
dops_util/global_var.py
dops_util/glue.py
dops_util/misc_info.py
dops_util/network.py
dops_util/organizations.py
dops_util/rds.py
dops_util/redshift.py
dops_util/s3.py
dops_util/service_catalog.py
dops_util.egg-info/PKG-INFO
dops_util.egg-info/SOURCES.txt
dops_util.egg-info/dependency_links.txt
dops_util.egg-info/requires.txt
dops_util.egg-info/top_level.txt