Metadata-Version: 2.1
Name: dops-util
Version: 0.1
Summary: hantu to monitor aws
Home-page: https://github.com/yourusername/yourpackage
Author: indra harahap
Author-email: indra.harahap@sema4.com
License: UNKNOWN
Platform: UNKNOWN
Classifier: Programming Language :: Python :: 3
Classifier: License :: OSI Approved :: MIT License
Classifier: Operating System :: OS Independent
